shorser.py
shorser-0.1.1.dist-info/LICENSE
shorser-0.1.1.dist-info/WHEEL
shorser-0.1.1.dist-info/METADATA
shorser-0.1.1.dist-info/RECORD
