Metadata-Version: 2.1
Name: shorser
Version: 0.1.1
Summary: a shorter serializer
Home-page: https://github.com/Cologler/shorser-python
License: MIT
Author: Cologler
Author-email: skyoflw@gmail.com
Requires-Python: >=3.9,<4.0
Classifier: License :: OSI Approved :: MIT License
Classifier: Programming Language :: Python :: 3
Classifier: Programming Language :: Python :: 3.9
